test.py
restorify/__init__.py
restorify/restorable.py
restorify/utils.py
restorify-1.0.3.dist-info/licenses/LICENSE.txt
restorify-1.0.3.dist-info/METADATA
restorify-1.0.3.dist-info/WHEEL
restorify-1.0.3.dist-info/top_level.txt
restorify-1.0.3.dist-info/RECORD
