Metadata-Version: 2.4
Name: restorify
Version: 1.0.3
Summary: Type-safe and eazy json-to-object-and-back conversions.
Author-email: tntnkn <anton@tonotonokon.com>
License-Expression: MIT
Project-URL: Homepage, https://github.com/tntnkn/restorify
Project-URL: Issues, https://github.com/tntnkn/restorify/issues
Classifier: Programming Language :: Python :: 3
Classifier: Operating System :: OS Independent
Requires-Python: >=3.9
License-File: LICENSE.txt
Dynamic: license-file
